app/__init__.py
my_yo_yo_test-0.1.0b3.dist-info/METADATA
my_yo_yo_test-0.1.0b3.dist-info/WHEEL
my_yo_yo_test-0.1.0b3.dist-info/RECORD
