Metadata-Version: 2.1
Name: my_yo_yo_test
Version: 0.1.0b3
Summary: some test
License: Apache-2.0
Author: Rami Mashkouk
Author-email: rami.n.mashkouk@gmail.com
Requires-Python: >=3.10,<4.0
Classifier: License :: OSI Approved :: Apache Software License
Classifier: Programming Language :: Python :: 3
Classifier: Programming Language :: Python :: 3.10
Classifier: Programming Language :: Python :: 3.11
Classifier: Programming Language :: Python :: 3.12
